{"cameraMode":{"drawMode":0,"name":"Shaded","section":"Shading Mode"},"sceneLighting":false,"audioPlay":false,"sceneViewState":{"showFog":true,"showMaterialUpdate":false,"showSkybox":false,"showFlares":true,"showImageEffects":true,"showParticleSystems":true,"showVisualEffectGraphs":true,"m_FxEnabled":true},"in2DMode":false,"pivot":{"x":-15.63444995880127,"y":-5.085529327392578,"z":-1.6318089962005616},"rotation":{"x":0.14781729876995088,"y":-0.703614354133606,"z":0.1536029428243637,"w":0.6779467463493347},"size":3.024744749069214,"orthographic":false}